prosper_bot/__init__.py
prosper_bot/allocation_strategy/__init__.py
prosper_bot/analytics/__init__.py
prosper_bot/bot/__init__.py
prosper_bot/bot/bot.py
prosper_bot/cli/__init__.py
prosper_bot/util/__init__.py
prosper_bot-0.7.7.dist-info/LICENSE
prosper_bot-0.7.7.dist-info/METADATA
prosper_bot-0.7.7.dist-info/WHEEL
prosper_bot-0.7.7.dist-info/entry_points.txt
prosper_bot-0.7.7.dist-info/RECORD
