Metadata-Version: 2.1
Name: prosper-bot
Version: 0.7.7
Summary: Trading bot for Prosper.com
Author: Graham Tibbitts
Author-email: graham.tibbitts@gmail.com
Requires-Python: >=3.9,<3.13
Classifier: License :: OSI Approved :: Apache Software License
Classifier: Operating System :: OS Independent
Classifier: Programming Language :: Python :: 3
Classifier: Programming Language :: Python :: 3.9
Classifier: Programming Language :: Python :: 3.10
Classifier: Programming Language :: Python :: 3.11
Classifier: Programming Language :: Python :: 3 :: Only
Classifier: Programming Language :: Python :: 3.12
Classifier: Programming Language :: Python :: 3.8
Classifier: Topic :: Office/Business :: Financial :: Investment
Requires-Dist: backoff (>=2.2.1,<3.0.0)
Requires-Dist: black (>=24.8.0,<25.0.0)
Requires-Dist: humanize (>=4.8.0,<5.0.0)
Requires-Dist: prosper-api[secure] (>=0.11.0,<0.12.0)
Requires-Dist: pytz (>=2024.1,<2025.0)
Requires-Dist: pyxirr (>=0.10.5,<0.11.0)
Requires-Dist: simplejson (>=3.19.2,<4.0.0)
